omnisoot/__init__.py
omnisoot/apps/__init__.py
omnisoot/apps/carbonization.py
omnisoot/apps/constants.py
omnisoot/apps/flame.py
omnisoot/apps/pahgrowth.py
omnisoot/apps/particledynamics.py
omnisoot/apps/plugins.py
omnisoot/apps/reactors.py
omnisoot/apps/solutionarray.py
omnisoot/apps/solutionmodifier.py
omnisoot/apps/sootgas.py
omnisoot/apps/sootthermo.py
omnisoot/apps/sootwrappers.py
omnisoot/apps/surfacereactions.py
omnisoot/apps/surfacesites.py
omnisoot/apps/utils.py
omnisoot/legacy/__init__.py
omnisoot/legacy/cpfr.py
omnisoot/legacy/eptlsoot.py
omnisoot/legacy/psr.py
omnisoot/lib/_omnisoot.pypy39-pp73-win_amd64.pyd
omnisoot-0.2.10.dist-info/METADATA
omnisoot-0.2.10.dist-info/WHEEL
omnisoot-0.2.10.dist-info/top_level.txt
omnisoot-0.2.10.dist-info/RECORD
