Metadata-Version: 2.1
Name: omnisoot
Version: 0.2.10
Summary: a computational tool for modeling soot
Author-email: Mo Adib <moademic@gmail.com>
Project-URL: Homepage, https://carleton.ca/eptl/people/336/
Keywords: computational,soot
Classifier: Programming Language :: Python :: 3
Requires-Python: >=3.7
Requires-Dist: scipy
Requires-Dist: numpy
Requires-Dist: cantera
